Workbook

Sheet Tables
A1: MACRS GDS, half-year convention (200% DB; 15-year is 150% DB)
A2: Year | B2: 3 | C2: 5 | D2: 7 | E2: 10 | F2: 15
A3: 1 | B3: 0.3333 | C3: 0.2 | D3: 0.1429 | E3: 0.1 | F3: 0.05
A4: 2 | B4: 0.4445 | C4: 0.32 | D4: 0.2449 | E4: 0.18 | F4: 0.095
A5: 3 | B5: 0.1481 | C5: 0.192 | D5: 0.1749 | E5: 0.144 | F5: 0.0855
A6: 4 | B6: 0.0741 | C6: 0.1152 | D6: 0.1249 | E6: 0.1152 | F6: 0.077
A7: 5 | C7: 0.1152 | D7: 0.0893 | E7: 0.0922 | F7: 0.0693
A8: 6 | C8: 0.0576 | D8: 0.0892 | E8: 0.0737 | F8: 0.0623
A9: 7 | D9: 0.0893 | E9: 0.0655 | F9: 0.059
A10: 8 | D10: 0.0446 | E10: 0.0655 | F10: 0.059
A11: 9 | E11: 0.0656 | F11: 0.0591
A12: 10 | E12: 0.0655 | F12: 0.059
A13: 11 | E13: 0.0328 | F13: 0.0591
A14: 12 | F14: 0.059
A15: 13 | F15: 0.0591
A16: 14 | F16: 0.059
A17: 15 | F17: 0.0591
A18: 16 | F18: 0.0295

Sheet Register
A1: FIXED ASSET REGISTER & ROLL-FORWARD
A3: Report year | B3: 2026
A4: Asset ID | B4: Description | C4: In service | D4: Cost | E4: Salvage | F4: Life (yrs) | G4: Tax class | H4: Bonus % | I4: Disposed | J4: Proceeds | K4: Mo. prior | L4: Mo. this yr | M4: Monthly dep | N4: Beg A/D | O4: Dep this yr | P4: A/D relieved | Q4: End A/D | R4: End cost | S4: NBV | T4: Gain/(loss) | U4: Tax yr | V4: MACRS % | W4: Tax dep | X4: _add | Y4: _disp | Z4: Check | AA4: _prior
A5: FA-0001 | B5: Crown FC 5200 forklift | C5: 45000 | D5: 28500 | E5: 2500 | F5: 7 | G5: 5 | H5: 0 | K5: =IF($C5="","",MAX(0,MIN($F5*12,($B$3-1-YEAR($C5))*12+13-MONTH($C5)))) -> 34 | L5: =IF($C5="","",IF(YEAR($C5)>$B$3,0,IF(AND($I5<>"",YEAR($I5)<$B$3),0,MAX(0,MIN(IF(AND($I5<>"",YEAR($I5)=$B$3),MONTH($I5)-1,12)-IF(YEAR($C5)=$B$3,MONTH($C5),1)+1,$F5*12-K5))))) -> 12 | M5: =IF($C5="","",IF($F5>0,MAX(0,$D5-$E5)/($F5*12),0)) -> 309.52381 | N5: =IF($C5="","",IF($AA5=1,0,K5*M5)) -> 10523.81 | O5: =IF($C5="","",L5*M5) -> 3714.2857 | P5: =IF($C5="",0,IF(Y5=1,N5+O5,0)) -> 0 | Q5: =IF($C5="","",IF(OR(Y5=1,$AA5=1),0,N5+O5)) -> 14238.095 | R5: =IF($C5="","",IF(OR(Y5=1,AND($I5<>"",YEAR($I5)<$B$3)),0,$D5)) -> 28500 | S5: =IF($C5="","",R5-Q5) -> 14261.905 | T5: =IF(Y5=1,$J5-($D5-P5),"") | U5: =IF($C5="","",$B$3-YEAR($C5)+1) -> 4 | V5: =IF($C5="","",IF(U5<1,0,IFERROR(INDEX(Tables!$B$3:$F$18,U5,MATCH($G5,Tables!$B$2:$F$2,0)),0))) -> 0.1152 | W5: =IF($C5="","",IF(OR($AA5=1,YEAR($C5)>$B$3),0,($D5*(1-$H5))*V5*IF(Y5=1,0.5,1)+IF(U5=1,$D5*$H5,0))) -> 3283.2 | X5: =IF($C5="",0,IF(YEAR($C5)=$B$3,1,0)) -> 0 | Y5: =IF($C5="",0,IF(AND($I5<>"",YEAR($I5)=$B$3),1,0)) -> 0 | Z5: =IF($C5="","",IF($F5<=0,"Life must be greater than 0",IF($D5<0,"Cost cannot be negative",IF($E5>$D5,"Salvage exceeds cost",IF(YEAR($C5)>$B$3,"In-service date is after the report year",IF(AND($I5<>"",$I5<$C5),"Disposal date is before in-service date",IF(ISNA(MATCH($G5,Tables!$B$2:$F$2,0)),"Tax class must be 3, 5, 7, 10 or 15",IF($AA5=1,"Disposed in a prior year - remove this row","OK")))))))) -> OK | AA5: =IF($C5="",0,IF(AND($I5<>"",YEAR($I5)<$B$3),1,0)) -> 0
A6: FA-0002 | B6: Office buildout, Suite 210 | C6: 45474 | D6: 64200 | E6: 0 | F6: 10 | G6: 15 | H6: 0 | K6: =IF($C6="","",MAX(0,MIN($F6*12,($B$3-1-YEAR($C6))*12+13-MONTH($C6)))) -> 18 | L6: =IF($C6="","",IF(YEAR($C6)>$B$3,0,IF(AND($I6<>"",YEAR($I6)<$B$3),0,MAX(0,MIN(IF(AND($I6<>"",YEAR($I6)=$B$3),MONTH($I6)-1,12)-IF(YEAR($C6)=$B$3,MONTH($C6),1)+1,$F6*12-K6))))) -> 12 | M6: =IF($C6="","",IF($F6>0,MAX(0,$D6-$E6)/($F6*12),0)) -> 535 | N6: =IF($C6="","",IF($AA6=1,0,K6*M6)) -> 9630 | O6: =IF($C6="","",L6*M6) -> 6420 | P6: =IF($C6="",0,IF(Y6=1,N6+O6,0)) -> 0 | Q6: =IF($C6="","",IF(OR(Y6=1,$AA6=1),0,N6+O6)) -> 16050 | R6: =IF($C6="","",IF(OR(Y6=1,AND($I6<>"",YEAR($I6)<$B$3)),0,$D6)) -> 64200 | S6: =IF($C6="","",R6-Q6) -> 48150 | T6: =IF(Y6=1,$J6-($D6-P6),"") | U6: =IF($C6="","",$B$3-YEAR($C6)+1) -> 3 | V6: =IF($C6="","",IF(U6<1,0,IFERROR(INDEX(Tables!$B$3:$F$18,U6,MATCH($G6,Tables!$B$2:$F$2,0)),0))) -> 0.0855 | W6: =IF($C6="","",IF(OR($AA6=1,YEAR($C6)>$B$3),0,($D6*(1-$H6))*V6*IF(Y6=1,0.5,1)+IF(U6=1,$D6*$H6,0))) -> 5489.1 | X6: =IF($C6="",0,IF(YEAR($C6)=$B$3,1,0)) -> 0 | Y6: =IF($C6="",0,IF(AND($I6<>"",YEAR($I6)=$B$3),1,0)) -> 0 | Z6: =IF($C6="","",IF($F6<=0,"Life must be greater than 0",IF($D6<0,"Cost cannot be negative",IF($E6>$D6,"Salvage exceeds cost",IF(YEAR($C6)>$B$3,"In-service date is after the report year",IF(AND($I6<>"",$I6<$C6),"Disposal date is before in-service date",IF(ISNA(MATCH($G6,Tables!$B$2:$F$2,0)),"Tax class must be 3, 5, 7, 10 or 15",IF($AA6=1,"Disposed in a prior year - remove this row","OK")))))))) -> OK | AA6: =IF($C6="",0,IF(AND($I6<>"",YEAR($I6)<$B$3),1,0)) -> 0
A7: FA-0003 | B7: Dell Latitude laptops (x6) | C7: 46042 | D7: 8940 | E7: 0 | F7: 3 | G7: 5 | H7: 0.8 | K7: =IF($C7="","",MAX(0,MIN($F7*12,($B$3-1-YEAR($C7))*12+13-MONTH($C7)))) -> 0 | L7: =IF($C7="","",IF(YEAR($C7)>$B$3,0,IF(AND($I7<>"",YEAR($I7)<$B$3),0,MAX(0,MIN(IF(AND($I7<>"",YEAR($I7)=$B$3),MONTH($I7)-1,12)-IF(YEAR($C7)=$B$3,MONTH($C7),1)+1,$F7*12-K7))))) -> 12 | M7: =IF($C7="","",IF($F7>0,MAX(0,$D7-$E7)/($F7*12),0)) -> 248.33333 | N7: =IF($C7="","",IF($AA7=1,0,K7*M7)) -> 0 | O7: =IF($C7="","",L7*M7) -> 2980 | P7: =IF($C7="",0,IF(Y7=1,N7+O7,0)) -> 0 | Q7: =IF($C7="","",IF(OR(Y7=1,$AA7=1),0,N7+O7)) -> 2980 | R7: =IF($C7="","",IF(OR(Y7=1,AND($I7<>"",YEAR($I7)<$B$3)),0,$D7)) -> 8940 | S7: =IF($C7="","",R7-Q7) -> 5960 | T7: =IF(Y7=1,$J7-($D7-P7),"") | U7: =IF($C7="","",$B$3-YEAR($C7)+1) -> 1 | V7: =IF($C7="","",IF(U7<1,0,IFERROR(INDEX(Tables!$B$3:$F$18,U7,MATCH($G7,Tables!$B$2:$F$2,0)),0))) -> 0.2 | W7: =IF($C7="","",IF(OR($AA7=1,YEAR($C7)>$B$3),0,($D7*(1-$H7))*V7*IF(Y7=1,0.5,1)+IF(U7=1,$D7*$H7,0))) -> 7509.6 | X7: =IF($C7="",0,IF(YEAR($C7)=$B$3,1,0)) -> 1 | Y7: =IF($C7="",0,IF(AND($I7<>"",YEAR($I7)=$B$3),1,0)) -> 0 | Z7: =IF($C7="","",IF($F7<=0,"Life must be greater than 0",IF($D7<0,"Cost cannot be negative",IF($E7>$D7,"Salvage exceeds cost",IF(YEAR($C7)>$B$3,"In-service date is after the report year",IF(AND($I7<>"",$I7<$C7),"Disposal date is before in-service date",IF(ISNA(MATCH($G7,Tables!$B$2:$F$2,0)),"Tax class must be 3, 5, 7, 10 or 15",IF($AA7=1,"Disposed in a prior year - remove this row","OK")))))))) -> OK | AA7: =IF($C7="",0,IF(AND($I7<>"",YEAR($I7)<$B$3),1,0)) -> 0
A8: FA-0004 | B8: Ford F-350 service truck | C8: 46122 | D8: 52800 | E8: 4800 | F8: 5 | G8: 5 | H8: 0 | K8: =IF($C8="","",MAX(0,MIN($F8*12,($B$3-1-YEAR($C8))*12+13-MONTH($C8)))) -> 0 | L8: =IF($C8="","",IF(YEAR($C8)>$B$3,0,IF(AND($I8<>"",YEAR($I8)<$B$3),0,MAX(0,MIN(IF(AND($I8<>"",YEAR($I8)=$B$3),MONTH($I8)-1,12)-IF(YEAR($C8)=$B$3,MONTH($C8),1)+1,$F8*12-K8))))) -> 9 | M8: =IF($C8="","",IF($F8>0,MAX(0,$D8-$E8)/($F8*12),0)) -> 800 | N8: =IF($C8="","",IF($AA8=1,0,K8*M8)) -> 0 | O8: =IF($C8="","",L8*M8) -> 7200 | P8: =IF($C8="",0,IF(Y8=1,N8+O8,0)) -> 0 | Q8: =IF($C8="","",IF(OR(Y8=1,$AA8=1),0,N8+O8)) -> 7200 | R8: =IF($C8="","",IF(OR(Y8=1,AND($I8<>"",YEAR($I8)<$B$3)),0,$D8)) -> 52800 | S8: =IF($C8="","",R8-Q8) -> 45600 | T8: =IF(Y8=1,$J8-($D8-P8),"") | U8: =IF($C8="","",$B$3-YEAR($C8)+1) -> 1 | V8: =IF($C8="","",IF(U8<1,0,IFERROR(INDEX(Tables!$B$3:$F$18,U8,MATCH($G8,Tables!$B$2:$F$2,0)),0))) -> 0.2 | W8: =IF($C8="","",IF(OR($AA8=1,YEAR($C8)>$B$3),0,($D8*(1-$H8))*V8*IF(Y8=1,0.5,1)+IF(U8=1,$D8*$H8,0))) -> 10560 | X8: =IF($C8="",0,IF(YEAR($C8)=$B$3,1,0)) -> 1 | Y8: =IF($C8="",0,IF(AND($I8<>"",YEAR($I8)=$B$3),1,0)) -> 0 | Z8: =IF($C8="","",IF($F8<=0,"Life must be greater than 0",IF($D8<0,"Cost cannot be negative",IF($E8>$D8,"Salvage exceeds cost",IF(YEAR($C8)>$B$3,"In-service date is after the report year",IF(AND($I8<>"",$I8<$C8),"Disposal date is before in-service date",IF(ISNA(MATCH($G8,Tables!$B$2:$F$2,0)),"Tax class must be 3, 5, 7, 10 or 15",IF($AA8=1,"Disposed in a prior year - remove this row","OK")))))))) -> OK | AA8: =IF($C8="",0,IF(AND($I8<>"",YEAR($I8)<$B$3),1,0)) -> 0
A9: FA-0005 | B9: Haas VF-2 CNC mill | C9: 44440 | D9: 145000 | E9: 5000 | F9: 10 | G9: 7 | H9: 0 | K9: =IF($C9="","",MAX(0,MIN($F9*12,($B$3-1-YEAR($C9))*12+13-MONTH($C9)))) -> 52 | L9: =IF($C9="","",IF(YEAR($C9)>$B$3,0,IF(AND($I9<>"",YEAR($I9)<$B$3),0,MAX(0,MIN(IF(AND($I9<>"",YEAR($I9)=$B$3),MONTH($I9)-1,12)-IF(YEAR($C9)=$B$3,MONTH($C9),1)+1,$F9*12-K9))))) -> 12 | M9: =IF($C9="","",IF($F9>0,MAX(0,$D9-$E9)/($F9*12),0)) -> 1166.6667 | N9: =IF($C9="","",IF($AA9=1,0,K9*M9)) -> 60666.667 | O9: =IF($C9="","",L9*M9) -> 14000 | P9: =IF($C9="",0,IF(Y9=1,N9+O9,0)) -> 0 | Q9: =IF($C9="","",IF(OR(Y9=1,$AA9=1),0,N9+O9)) -> 74666.667 | R9: =IF($C9="","",IF(OR(Y9=1,AND($I9<>"",YEAR($I9)<$B$3)),0,$D9)) -> 145000 | S9: =IF($C9="","",R9-Q9) -> 70333.333 | T9: =IF(Y9=1,$J9-($D9-P9),"") | U9: =IF($C9="","",$B$3-YEAR($C9)+1) -> 6 | V9: =IF($C9="","",IF(U9<1,0,IFERROR(INDEX(Tables!$B$3:$F$18,U9,MATCH($G9,Tables!$B$2:$F$2,0)),0))) -> 0.0892 | W9: =IF($C9="","",IF(OR($AA9=1,YEAR($C9)>$B$3),0,($D9*(1-$H9))*V9*IF(Y9=1,0.5,1)+IF(U9=1,$D9*$H9,0))) -> 12934 | X9: =IF($C9="",0,IF(YEAR($C9)=$B$3,1,0)) -> 0 | Y9: =IF($C9="",0,IF(AND($I9<>"",YEAR($I9)=$B$3),1,0)) -> 0 | Z9: =IF($C9="","",IF($F9<=0,"Life must be greater than 0",IF($D9<0,"Cost cannot be negative",IF($E9>$D9,"Salvage exceeds cost",IF(YEAR($C9)>$B$3,"In-service date is after the report year",IF(AND($I9<>"",$I9<$C9),"Disposal date is before in-service date",IF(ISNA(MATCH($G9,Tables!$B$2:$F$2,0)),"Tax class must be 3, 5, 7, 10 or 15",IF($AA9=1,"Disposed in a prior year - remove this row","OK")))))))) -> OK | AA9: =IF($C9="",0,IF(AND($I9<>"",YEAR($I9)<$B$3),1,0)) -> 0
A10: FA-0006 | B10: Dell PowerEdge server | C10: 44693 | D10: 18600 | E10: 0 | F10: 5 | G10: 5 | H10: 0 | I10: 46188 | J10: 4200 | K10: =IF($C10="","",MAX(0,MIN($F10*12,($B$3-1-YEAR($C10))*12+13-MONTH($C10)))) -> 44 | L10: =IF($C10="","",IF(YEAR($C10)>$B$3,0,IF(AND($I10<>"",YEAR($I10)<$B$3),0,MAX(0,MIN(IF(AND($I10<>"",YEAR($I10)=$B$3),MONTH($I10)-1,12)-IF(YEAR($C10)=$B$3,MONTH($C10),1)+1,$F10*12-K10))))) -> 5 | M10: =IF($C10="","",IF($F10>0,MAX(0,$D10-$E10)/($F10*12),0)) -> 310 | N10: =IF($C10="","",IF($AA10=1,0,K10*M10)) -> 13640 | O10: =IF($C10="","",L10*M10) -> 1550 | P10: =IF($C10="",0,IF(Y10=1,N10+O10,0)) -> 15190 | Q10: =IF($C10="","",IF(OR(Y10=1,$AA10=1),0,N10+O10)) -> 0 | R10: =IF($C10="","",IF(OR(Y10=1,AND($I10<>"",YEAR($I10)<$B$3)),0,$D10)) -> 0 | S10: =IF($C10="","",R10-Q10) -> 0 | T10: =IF(Y10=1,$J10-($D10-P10),"") -> 790 | U10: =IF($C10="","",$B$3-YEAR($C10)+1) -> 5 | V10: =IF($C10="","",IF(U10<1,0,IFERROR(INDEX(Tables!$B$3:$F$18,U10,MATCH($G10,Tables!$B$2:$F$2,0)),0))) -> 0.1152 | W10: =IF($C10="","",IF(OR($AA10=1,YEAR($C10)>$B$3),0,($D10*(1-$H10))*V10*IF(Y10=1,0.5,1)+IF(U10=1,$D10*$H10,0))) -> 1071.36 | X10: =IF($C10="",0,IF(YEAR($C10)=$B$3,1,0)) -> 0 | Y10: =IF($C10="",0,IF(AND($I10<>"",YEAR($I10)=$B$3),1,0)) -> 1 | Z10: =IF($C10="","",IF($F10<=0,"Life must be greater than 0",IF($D10<0,"Cost cannot be negative",IF($E10>$D10,"Salvage exceeds cost",IF(YEAR($C10)>$B$3,"In-service date is after the report year",IF(AND($I10<>"",$I10<$C10),"Disposal date is before in-service date",IF(ISNA(MATCH($G10,Tables!$B$2:$F$2,0)),"Tax class must be 3, 5, 7, 10 or 15",IF($AA10=1,"Disposed in a prior year - remove this row","OK")))))))) -> OK | AA10: =IF($C10="",0,IF(AND($I10<>"",YEAR($I10)<$B$3),1,0)) -> 0
B11: TOTALS | D11: =SUM(D5:D10) -> 318040 | J11: =SUM(J5:J10) -> 4200 | N11: =SUM(N5:N10) -> 94460.476 | O11: =SUM(O5:O10) -> 35864.286 | P11: =SUM(P5:P10) -> 15190 | Q11: =SUM(Q5:Q10) -> 115134.76 | R11: =SUM(R5:R10) -> 299440 | S11: =SUM(S5:S10) -> 184305.24 | T11: =SUM(T5:T10) -> 790 | W11: =SUM(W5:W10) -> 40847.26
A14: ROLL-FORWARD | B14: Cost | C14: Accum. dep.
A15: Beginning | B15: =SUMPRODUCT(($C$5:$C$10<>"")*(1-$X$5:$X$10)*(1-$AA$5:$AA$10)*$D$5:$D$10) -> 256300 | C15: =$N$11 -> 94460.476
A16: Additions / depreciation | B16: =SUMPRODUCT($X$5:$X$10*$D$5:$D$10) -> 61740 | C16: =$O$11 -> 35864.286
A17: Disposals / A/D relieved | B17: =-SUMPRODUCT($Y$5:$Y$10*$D$5:$D$10) -> -18600 | C17: =-$P$11 -> -15190
A18: Ending | B18: =SUM(B15:B17) -> 299440 | C18: =SUM(C15:C17) -> 115134.76
A19: Ties to detail? | B19: =IF(ROUND(B18-$R$11,2)=0,"OK",B18-$R$11) -> OK | C19: =IF(ROUND(C18-$Q$11,2)=0,"OK",C18-$Q$11) -> OK
A20: Net book value | B20: =B18-C18 -> 184305.24
A21: Ties to detail? | B21: =IF(ROUND(B20-$S$11,2)=0,"OK",B20-$S$11) -> OK
A22: Input check | B22: =IF(SUMPRODUCT(($C$5:$C$10<>"")*($Z$5:$Z$10<>"OK"))=0,"OK",SUMPRODUCT(($C$5:$C$10<>"")*($Z$5:$Z$10<>"OK"))&" row(s) need attention - see Check column") -> OK
A23: TIE TO GL
A24: GL fixed asset cost | C24: =IF($B24="","enter GL balance",IF(ROUND($B24-B18,2)=0,"OK",$B24-B18)) -> enter GL balance
A25: GL accumulated depreciation | C25: =IF($B25="","enter GL balance",IF(ROUND($B25-C18,2)=0,"OK",$B25-C18)) -> enter GL balance

Sheet Readme
A1: FIXED ASSET REGISTER & ROLL-FORWARD, from smbsolved.com
A3: Yellow cells are inputs. Everything else calculates.
A4: Book depreciation is straight line, full-month convention: the month you place an asset in service counts, the month you dispose of it does not.
A5: Tax depreciation is MACRS GDS half-year (percentages on the Tables sheet). Bonus % applies in year one and reduces the MACRS basis. Section 179 is not modeled; ask your tax preparer.
A6: The Check column flags bad inputs row by row, and the Input check line under the roll-forward counts how many rows need attention. Both should read OK.
A7: The tie-out rows should read OK. If one shows a number, that number is exactly how far off you are.
A8: Assets disposed of in a year before the report year carry no cost and no accumulated depreciation, so the roll-forward still ties. The Check column will tell you to remove the row.
A9: Add rows: insert above the TOTALS row, then fill the formulas down from the row above. Extend the SUM and SUMPRODUCT ranges in the totals and roll-forward to cover the new rows.
A10: Tax classes supported: 3, 5, 7, 10 and 15 year. Real property (20, 27.5 and 39 year) uses a mid-month convention and is not modeled.
A11: Columns X, Y and AA are hidden helper flags. Leave them alone.
A12: No macros. Works in Excel 2016 and later.
